wavelet_transform_contracts/__init__.py
wavelet_transform_contracts/wavelet_transform_service_pb2.py
wavelet_transform_contracts/wavelet_transform_service_pb2_grpc.py
wavelet_transform_contracts-1.0.5.dist-info/METADATA
wavelet_transform_contracts-1.0.5.dist-info/WHEEL
wavelet_transform_contracts-1.0.5.dist-info/top_level.txt
wavelet_transform_contracts-1.0.5.dist-info/RECORD
